cyberfusion/CoreApiClient/__init__.py
cyberfusion/CoreApiClient/_encoders.py
cyberfusion/CoreApiClient/_helpers.py
cyberfusion/CoreApiClient/connector.py
cyberfusion/CoreApiClient/exceptions.py
cyberfusion/CoreApiClient/http.py
cyberfusion/CoreApiClient/interfaces.py
cyberfusion/CoreApiClient/models.py
cyberfusion/CoreApiClient/resources/__init__.py
cyberfusion/CoreApiClient/resources/basic_authentication_realms.py
cyberfusion/CoreApiClient/resources/borg_archives.py
cyberfusion/CoreApiClient/resources/borg_repositories.py
cyberfusion/CoreApiClient/resources/certificate_managers.py
cyberfusion/CoreApiClient/resources/certificates.py
cyberfusion/CoreApiClient/resources/clusters.py
cyberfusion/CoreApiClient/resources/cmses.py
cyberfusion/CoreApiClient/resources/crons.py
cyberfusion/CoreApiClient/resources/custom_config_snippets.py
cyberfusion/CoreApiClient/resources/custom_configs.py
cyberfusion/CoreApiClient/resources/customers.py
cyberfusion/CoreApiClient/resources/daemons.py
cyberfusion/CoreApiClient/resources/database_user_grants.py
cyberfusion/CoreApiClient/resources/database_users.py
cyberfusion/CoreApiClient/resources/databases.py
cyberfusion/CoreApiClient/resources/domain_routers.py
cyberfusion/CoreApiClient/resources/firewall_groups.py
cyberfusion/CoreApiClient/resources/firewall_rules.py
cyberfusion/CoreApiClient/resources/fpm_pools.py
cyberfusion/CoreApiClient/resources/ftp_users.py
cyberfusion/CoreApiClient/resources/haproxy_listens.py
cyberfusion/CoreApiClient/resources/haproxy_listens_to_nodes.py
cyberfusion/CoreApiClient/resources/health.py
cyberfusion/CoreApiClient/resources/hosts_entries.py
cyberfusion/CoreApiClient/resources/htpasswd_files.py
cyberfusion/CoreApiClient/resources/htpasswd_users.py
cyberfusion/CoreApiClient/resources/login.py
cyberfusion/CoreApiClient/resources/logs.py
cyberfusion/CoreApiClient/resources/mail_accounts.py
cyberfusion/CoreApiClient/resources/mail_aliases.py
cyberfusion/CoreApiClient/resources/mail_domains.py
python3_core_api_client-2.12.1.dist-info/METADATA
python3_core_api_client-2.12.1.dist-info/WHEEL
python3_core_api_client-2.12.1.dist-info/top_level.txt
python3_core_api_client-2.12.1.dist-info/RECORD
