Metadata-Version: 2.4
Name: python3-core-api-client
Version: 2.12.1
Summary: Python client for Core API.
Author-email: Cyberfusion <support@cyberfusion.io>
Project-URL: Source, https://github.com/CyberfusionIO/python3-core-api-client
Requires-Dist: certifi==2025.11.12
Requires-Dist: requests==2.32.5
Requires-Dist: pydantic[email]==2.12.5
